{"name":"Successful login","id":"login;successful-login","testSteps":[{"number":1,"description":"Given I am on the login page","duration":63789,"startTime":"2023-09-25T17:59:04.542491400-05:00[America/Bogota]","screenshots":[{"screenshot":"1fbef1e449eff339a105f7593fc1aa8d5d0e8195ec682a34ccf46b664fc8619b.png","timeStamp":1695682808332,"screenshotName":"1fbef1e449eff339a105f7593fc1aa8d5d0e8195ec682a34ccf46b664fc8619b.png"}],"result":"SUCCESS","precondition":false,"level":0,"children":[{"number":2,"description":"user opens the Qa page","duration":63038,"startTime":"2023-09-25T17:59:05.248885100-05:00[America/Bogota]","screenshots":[{"screenshot":"1fbef1e449eff339a105f7593fc1aa8d5d0e8195ec682a34ccf46b664fc8619b.png","timeStamp":1695682808287,"screenshotName":"1fbef1e449eff339a105f7593fc1aa8d5d0e8195ec682a34ccf46b664fc8619b.png"}],"result":"SUCCESS","precondition":false,"level":1}]},{"number":3,"description":"When I enter valid credentials","duration":111217,"startTime":"2023-09-25T18:00:08.332476-05:00[America/Bogota]","screenshots":[{"screenshot":"1fbef1e449eff339a105f7593fc1aa8d5d0e8195ec682a34ccf46b664fc8619b.png","htmlSource":"pagesource4403035622179144770.html","timeStamp":1695682808832,"screenshotName":"1fbef1e449eff339a105f7593fc1aa8d5d0e8195ec682a34ccf46b664fc8619b.png"}],"exception":{"errorType":"java.lang.AssertionError","message":"\r\nExpected: an element that is currently visible\r\n     but: no matching element found by [ Button process declarations of change located with: xpath: /html/body/app-sub-root/app-root/div/app-horizontal-menu/div/nav/div/ul/li[2]/a] was not visible","stackTrace":[{"declaringClass":"co.com.choucair.certification.proyectobase.tasks.Login","methodName":"performAs","fileName":"Login.java","lineNumber":27},{"declaringClass":"co.com.choucair.certification.proyectobase.stepdefinitions.LoginStepDefinitions","methodName":"iEnterValidCredentials","fileName":"LoginStepDefinitions.java","lineNumber":41},{"declaringClass":"io.cucumber.java.Invoker","methodName":"doInvoke","fileName":"Invoker.java","lineNumber":66},{"declaringClass":"io.cucumber.java.Invoker","methodName":"invoke","fileName":"Invoker.java","lineNumber":24},{"declaringClass":"io.cucumber.java.AbstractGlueDefinition","methodName":"invokeMethod","fileName":"AbstractGlueDefinition.java","lineNumber":47},{"declaringClass":"io.cucumber.java.JavaStepDefinition","methodName":"execute","fileName":"JavaStepDefinition.java","lineNumber":29},{"declaringClass":"io.cucumber.core.runner.CoreStepDefinition","methodName":"execute","fileName":"CoreStepDefinition.java","lineNumber":66},{"declaringClass":"io.cucumber.core.runner.PickleStepDefinitionMatch","methodName":"runStep","fileName":"PickleStepDefinitionMatch.java","lineNumber":63},{"declaringClass":"io.cucumber.core.runner.TestStep","methodName":"executeStep","fileName":"TestStep.java","lineNumber":85},{"declaringClass":"io.cucumber.core.runner.TestStep","methodName":"run","fileName":"TestStep.java","lineNumber":57},{"declaringClass":"io.cucumber.core.runner.PickleStepTestStep","methodName":"run","fileName":"PickleStepTestStep.java","lineNumber":51},{"declaringClass":"io.cucumber.core.runner.TestCase","methodName":"run","fileName":"TestCase.java","lineNumber":84},{"declaringClass":"io.cucumber.core.runner.Runner","methodName":"runPickle","fileName":"Runner.java","lineNumber":75},{"declaringClass":"io.cucumber.core.runtime.CucumberExecutionContext","methodName":"lambda$runTestCase$5","fileName":"CucumberExecutionContext.java","lineNumber":129},{"declaringClass":"io.cucumber.core.runtime.RethrowingThrowableCollector","methodName":"executeAndThrow","fileName":"RethrowingThrowableCollector.java","lineNumber":23},{"declaringClass":"io.cucumber.core.runtime.CucumberExecutionContext","methodName":"runTestCase","fileName":"CucumberExecutionContext.java","lineNumber":129},{"declaringClass":"io.cucumber.junit.FeatureRunner","methodName":"runChild","fileName":"FeatureRunner.java","lineNumber":144},{"declaringClass":"io.cucumber.junit.FeatureRunner","methodName":"runChild","fileName":"FeatureRunner.java","lineNumber":28},{"declaringClass":"io.cucumber.junit.FeatureRunner","methodName":"run","fileName":"FeatureRunner.java","lineNumber":137},{"declaringClass":"io.cucumber.junit.CucumberSerenityRunner","methodName":"runChild","fileName":"CucumberSerenityRunner.java","lineNumber":259},{"declaringClass":"io.cucumber.junit.CucumberSerenityRunner","methodName":"runChild","fileName":"CucumberSerenityRunner.java","lineNumber":59},{"declaringClass":"worker.org.gradle.process.internal.worker.GradleWorkerMain","methodName":"run","fileName":"GradleWorkerMain.java","lineNumber":69},{"declaringClass":"worker.org.gradle.process.internal.worker.GradleWorkerMain","methodName":"main","fileName":"GradleWorkerMain.java","lineNumber":74}]},"result":"FAILURE","precondition":false,"level":0,"children":[{"number":4,"description":"User login","duration":110657,"startTime":"2023-09-25T18:00:08.857968100-05:00[America/Bogota]","screenshots":[{"screenshot":"042125234fb2805e7135bffee1ee24b061811ea86980d79b70bfee3303c6ff17.png","htmlSource":"pagesource11840792017749972650.html","timeStamp":1695682919508,"screenshotName":"042125234fb2805e7135bffee1ee24b061811ea86980d79b70bfee3303c6ff17.png"}],"exception":{"errorType":"java.lang.AssertionError","message":"\r\nExpected: an element that is currently visible\r\n     but: no matching element found by [ Button process declarations of change located with: xpath: /html/body/app-sub-root/app-root/div/app-horizontal-menu/div/nav/div/ul/li[2]/a] was not visible","stackTrace":[{"declaringClass":"co.com.choucair.certification.proyectobase.tasks.Login","methodName":"performAs","fileName":"Login.java","lineNumber":27},{"declaringClass":"co.com.choucair.certification.proyectobase.stepdefinitions.LoginStepDefinitions","methodName":"iEnterValidCredentials","fileName":"LoginStepDefinitions.java","lineNumber":41},{"declaringClass":"io.cucumber.java.Invoker","methodName":"doInvoke","fileName":"Invoker.java","lineNumber":66},{"declaringClass":"io.cucumber.java.Invoker","methodName":"invoke","fileName":"Invoker.java","lineNumber":24},{"declaringClass":"io.cucumber.java.AbstractGlueDefinition","methodName":"invokeMethod","fileName":"AbstractGlueDefinition.java","lineNumber":47},{"declaringClass":"io.cucumber.java.JavaStepDefinition","methodName":"execute","fileName":"JavaStepDefinition.java","lineNumber":29},{"declaringClass":"io.cucumber.core.runner.CoreStepDefinition","methodName":"execute","fileName":"CoreStepDefinition.java","lineNumber":66},{"declaringClass":"io.cucumber.core.runner.PickleStepDefinitionMatch","methodName":"runStep","fileName":"PickleStepDefinitionMatch.java","lineNumber":63},{"declaringClass":"io.cucumber.core.runner.TestStep","methodName":"executeStep","fileName":"TestStep.java","lineNumber":85},{"declaringClass":"io.cucumber.core.runner.TestStep","methodName":"run","fileName":"TestStep.java","lineNumber":57},{"declaringClass":"io.cucumber.core.runner.PickleStepTestStep","methodName":"run","fileName":"PickleStepTestStep.java","lineNumber":51},{"declaringClass":"io.cucumber.core.runner.TestCase","methodName":"run","fileName":"TestCase.java","lineNumber":84},{"declaringClass":"io.cucumber.core.runner.Runner","methodName":"runPickle","fileName":"Runner.java","lineNumber":75},{"declaringClass":"io.cucumber.core.runtime.CucumberExecutionContext","methodName":"lambda$runTestCase$5","fileName":"CucumberExecutionContext.java","lineNumber":129},{"declaringClass":"io.cucumber.core.runtime.RethrowingThrowableCollector","methodName":"executeAndThrow","fileName":"RethrowingThrowableCollector.java","lineNumber":23},{"declaringClass":"io.cucumber.core.runtime.CucumberExecutionContext","methodName":"runTestCase","fileName":"CucumberExecutionContext.java","lineNumber":129},{"declaringClass":"io.cucumber.junit.FeatureRunner","methodName":"runChild","fileName":"FeatureRunner.java","lineNumber":144},{"declaringClass":"io.cucumber.junit.FeatureRunner","methodName":"runChild","fileName":"FeatureRunner.java","lineNumber":28},{"declaringClass":"io.cucumber.junit.FeatureRunner","methodName":"run","fileName":"FeatureRunner.java","lineNumber":137},{"declaringClass":"io.cucumber.junit.CucumberSerenityRunner","methodName":"runChild","fileName":"CucumberSerenityRunner.java","lineNumber":259},{"declaringClass":"io.cucumber.junit.CucumberSerenityRunner","methodName":"runChild","fileName":"CucumberSerenityRunner.java","lineNumber":59},{"declaringClass":"worker.org.gradle.process.internal.worker.GradleWorkerMain","methodName":"run","fileName":"GradleWorkerMain.java","lineNumber":69},{"declaringClass":"worker.org.gradle.process.internal.worker.GradleWorkerMain","methodName":"main","fileName":"GradleWorkerMain.java","lineNumber":74}]},"result":"FAILURE","precondition":false,"level":1,"children":[{"number":5,"description":"user enters \u0027geortiz1\u0027 into USER","duration":1147,"startTime":"2023-09-25T18:00:09.866321500-05:00[America/Bogota]","screenshots":[{"screenshot":"a78e7c47c70f9e03fa6c1ca96d92176fe45e858d7317f9868c5ab55b455860de.png","timeStamp":1695682811013,"screenshotName":"a78e7c47c70f9e03fa6c1ca96d92176fe45e858d7317f9868c5ab55b455860de.png"}],"result":"SUCCESS","precondition":false,"level":2},{"number":6,"description":"user enters \u0027bbbbbbbb\u0027 into PASSWORD","duration":1034,"startTime":"2023-09-25T18:00:11.168323800-05:00[America/Bogota]","screenshots":[{"screenshot":"0fe3ff0554132ac2c3cf1ca111543459b5012a43baba7a3846455247e25439f1.png","htmlSource":"pagesource17369298751429365873.html","timeStamp":1695682811559,"screenshotName":"0fe3ff0554132ac2c3cf1ca111543459b5012a43baba7a3846455247e25439f1.png"},{"screenshot":"c988dfdc38b583ccfaf0f46df0f3ce17b2a10a8f35265aa299549fce00d7551a.png","timeStamp":1695682812202,"screenshotName":"c988dfdc38b583ccfaf0f46df0f3ce17b2a10a8f35265aa299549fce00d7551a.png"}],"result":"SUCCESS","precondition":false,"level":2},{"number":7,"description":"user clicks on Accept Button Tester","duration":1120,"startTime":"2023-09-25T18:00:12.340638800-05:00[America/Bogota]","screenshots":[{"screenshot":"911562799f2bfce164fbc3581ec46ad11a6545063029ccb479b34caa6634a1d2.png","htmlSource":"pagesource8807531615129673267.html","timeStamp":1695682812698,"screenshotName":"911562799f2bfce164fbc3581ec46ad11a6545063029ccb479b34caa6634a1d2.png"},{"screenshot":"4a4516a792ed63b5c1e1ec3e65e10ba8817515be52a808c03d86a674b6d1801d.png","timeStamp":1695682813461,"screenshotName":"4a4516a792ed63b5c1e1ec3e65e10ba8817515be52a808c03d86a674b6d1801d.png"}],"result":"SUCCESS","precondition":false,"level":2},{"number":8,"description":"user clicks on  Button app","duration":1115,"startTime":"2023-09-25T18:00:56.854008300-05:00[America/Bogota]","screenshots":[{"screenshot":"6b5e6ac2c4713656180932d3273efa41f4080ed32018332d90ce61c02d268484.png","htmlSource":"pagesource17828705936217888561.html","timeStamp":1695682857190,"screenshotName":"6b5e6ac2c4713656180932d3273efa41f4080ed32018332d90ce61c02d268484.png"},{"screenshot":"73446b5e52971427503a4ac2f339445fa42730a252ef2ebb85a3695b3f5d4dcd.png","timeStamp":1695682857969,"screenshotName":"73446b5e52971427503a4ac2f339445fa42730a252ef2ebb85a3695b3f5d4dcd.png"}],"result":"SUCCESS","precondition":false,"level":2}]}]},{"number":9,"description":"When I enter valid credentials","duration":43,"startTime":"2023-09-25T18:01:59.598309500-05:00[America/Bogota]","exception":{"errorType":"java.lang.AssertionError","message":"\r\nExpected: an element that is currently visible\r\n     but: no matching element found by [ Button process declarations of change located with: xpath: /html/body/app-sub-root/app-root/div/app-horizontal-menu/div/nav/div/ul/li[2]/a] was not visible","stackTrace":[{"declaringClass":"co.com.choucair.certification.proyectobase.tasks.Login","methodName":"performAs","fileName":"Login.java","lineNumber":27},{"declaringClass":"co.com.choucair.certification.proyectobase.stepdefinitions.LoginStepDefinitions","methodName":"iEnterValidCredentials","fileName":"LoginStepDefinitions.java","lineNumber":41},{"declaringClass":"✽","methodName":"I enter valid credentials","fileName":"file:///C:/Users/wmaldonado/Documents/automatizaciones/Base_Automatizacion/src/test/resources/features/loginhdc.feature","lineNumber":10}]},"result":"FAILURE","precondition":false,"level":0},{"number":10,"description":"Given I go to Menu commerce International and enter HDC app","duration":36,"startTime":"2023-09-25T18:01:59.645166200-05:00[America/Bogota]","result":"SKIPPED","precondition":false,"level":0},{"number":11,"description":"Then I see the message \"i\"","duration":32,"startTime":"2023-09-25T18:01:59.682711500-05:00[America/Bogota]","result":"SKIPPED","precondition":false,"level":0}],"userStory":{"id":"login","storyName":"Login","displayName":"Login","path":"loginhdc.feature","narrative":"  As a user\n  I want to login to the application\n  So that I can access my account","type":"feature"},"featureTag":{"name":"Login","type":"feature","displayName":"Login"},"title":"Successful login","description":"","tags":[{"name":"Login","type":"feature","displayName":"Login"},{"name":"stories","type":"tag","displayName":"stories"}],"startTime":"2023-09-25T17:59:04.091644800-05:00[America/Bogota]","duration":175641,"testFailureCause":{"errorType":"java.lang.AssertionError","message":"\r\nExpected: an element that is currently visible\r\n     but: no matching element found by [ Button process declarations of change located with: xpath: /html/body/app-sub-root/app-root/div/app-horizontal-menu/div/nav/div/ul/li[2]/a] was not visible","stackTrace":[{"declaringClass":"co.com.choucair.certification.proyectobase.tasks.Login","methodName":"performAs","fileName":"Login.java","lineNumber":27},{"declaringClass":"co.com.choucair.certification.proyectobase.stepdefinitions.LoginStepDefinitions","methodName":"iEnterValidCredentials","fileName":"LoginStepDefinitions.java","lineNumber":41},{"declaringClass":"io.cucumber.java.Invoker","methodName":"doInvoke","fileName":"Invoker.java","lineNumber":66},{"declaringClass":"io.cucumber.java.Invoker","methodName":"invoke","fileName":"Invoker.java","lineNumber":24},{"declaringClass":"io.cucumber.java.AbstractGlueDefinition","methodName":"invokeMethod","fileName":"AbstractGlueDefinition.java","lineNumber":47},{"declaringClass":"io.cucumber.java.JavaStepDefinition","methodName":"execute","fileName":"JavaStepDefinition.java","lineNumber":29},{"declaringClass":"io.cucumber.core.runner.CoreStepDefinition","methodName":"execute","fileName":"CoreStepDefinition.java","lineNumber":66},{"declaringClass":"io.cucumber.core.runner.PickleStepDefinitionMatch","methodName":"runStep","fileName":"PickleStepDefinitionMatch.java","lineNumber":63},{"declaringClass":"io.cucumber.core.runner.TestStep","methodName":"executeStep","fileName":"TestStep.java","lineNumber":85},{"declaringClass":"io.cucumber.core.runner.TestStep","methodName":"run","fileName":"TestStep.java","lineNumber":57},{"declaringClass":"io.cucumber.core.runner.PickleStepTestStep","methodName":"run","fileName":"PickleStepTestStep.java","lineNumber":51},{"declaringClass":"io.cucumber.core.runner.TestCase","methodName":"run","fileName":"TestCase.java","lineNumber":84},{"declaringClass":"io.cucumber.core.runner.Runner","methodName":"runPickle","fileName":"Runner.java","lineNumber":75},{"declaringClass":"io.cucumber.core.runtime.CucumberExecutionContext","methodName":"lambda$runTestCase$5","fileName":"CucumberExecutionContext.java","lineNumber":129},{"declaringClass":"io.cucumber.core.runtime.RethrowingThrowableCollector","methodName":"executeAndThrow","fileName":"RethrowingThrowableCollector.java","lineNumber":23},{"declaringClass":"io.cucumber.core.runtime.CucumberExecutionContext","methodName":"runTestCase","fileName":"CucumberExecutionContext.java","lineNumber":129},{"declaringClass":"io.cucumber.junit.FeatureRunner","methodName":"runChild","fileName":"FeatureRunner.java","lineNumber":144},{"declaringClass":"io.cucumber.junit.FeatureRunner","methodName":"runChild","fileName":"FeatureRunner.java","lineNumber":28},{"declaringClass":"io.cucumber.junit.FeatureRunner","methodName":"run","fileName":"FeatureRunner.java","lineNumber":137},{"declaringClass":"io.cucumber.junit.CucumberSerenityRunner","methodName":"runChild","fileName":"CucumberSerenityRunner.java","lineNumber":259},{"declaringClass":"io.cucumber.junit.CucumberSerenityRunner","methodName":"runChild","fileName":"CucumberSerenityRunner.java","lineNumber":59},{"declaringClass":"worker.org.gradle.process.internal.worker.GradleWorkerMain","methodName":"run","fileName":"GradleWorkerMain.java","lineNumber":69},{"declaringClass":"worker.org.gradle.process.internal.worker.GradleWorkerMain","methodName":"main","fileName":"GradleWorkerMain.java","lineNumber":74}]},"testFailureClassname":"java.lang.AssertionError","testFailureMessage":"\r\nExpected: an element that is currently visible\r\n     but: no matching element found by [ Button process declarations of change located with: xpath: /html/body/app-sub-root/app-root/div/app-horizontal-menu/div/nav/div/ul/li[2]/a] was not visible","testFailureSummary":"FAILURE;java.lang.AssertionError;\r\nExpected: an element that is currently visible\r\n     but: no matching element found by [ Button process declarations of change located with: xpath: /html/body/app-sub-root/app-root/div/app-horizontal-menu/div/nav/div/ul/li[2]/a] was not visible;Login.java","projectKey":"","annotatedResult":"FAILURE","sessionId":"3fcb0cc6242913bfd11d909bbdd312d9","driver":"chrome:user","isManualTestingUpToDate":false,"manual":false,"testSource":"Cucumber","actors":[{"name":"user","can":["browse the web"]}],"result":"FAILURE"}